LICENSE
README.md
pyproject.toml
setup.py
romanization.egg-info/PKG-INFO
romanization.egg-info/SOURCES.txt
romanization.egg-info/dependency_links.txt
romanization.egg-info/top_level.txt
src/romanization/__init__.py
src/romanization/const.py
src/romanization/romanize.py
tests/test_romanize.py